bing_brush/bing_brush.py
bing_brush/cli.py
examples/example.py
bing_brush-0.1.2.dist-info/METADATA
bing_brush-0.1.2.dist-info/WHEEL
bing_brush-0.1.2.dist-info/entry_points.txt
bing_brush-0.1.2.dist-info/RECORD
