Metadata-Version: 2.1
Name: bing_brush
Version: 0.1.2
Summary: One-line Image Generating Program Based on the Bing Image Createor (Powered by DALL·E 3)
Project-URL: Homepage, https://github.com/vra/bing_brush
Project-URL: Bug Tracker, https://github.com/vra/bing_brush/issues
Author-email: Yunfeng Wang <wyf.brz@gmail.com>
Classifier: License :: OSI Approved :: MIT License
Classifier: Operating System :: OS Independent
Classifier: Programming Language :: Python :: 3
Requires-Python: >=3.8
Requires-Dist: click
Requires-Dist: regex
Requires-Dist: requests
